hotcore/__init__.py
hotcore/_optional.py
hotcore/_version.py
hotcore/connection.py
hotcore/geospatial.py
hotcore/h3_index.py
hotcore/hotcore.py
hotcore/model.py
hotcore/relationships.py
hotcore/search.py
hotcore/storage.py
hotcore-1.2.1.dist-info/licenses/LICENSE
hotcore-1.2.1.dist-info/METADATA
hotcore-1.2.1.dist-info/WHEEL
hotcore-1.2.1.dist-info/top_level.txt
hotcore-1.2.1.dist-info/RECORD
