Metadata-Version: 2.4
Name: hotcore
Version: 1.2.1
Summary: A Redis-based hierarchical entity model for application data management
Author-email: Magnus Dahl <magnus.dahl@consistis.com>
License: MIT License
Project-URL: Homepage, https://github.com/Consistis-R-D/hotcore
Project-URL: Repository, https://github.com/Consistis-R-D/hotcore
Keywords: redis,data-model,geospatial,hierarchical
Classifier: Programming Language :: Python :: 3
Classifier: Programming Language :: Python :: 3 :: Only
Classifier: Programming Language :: Python :: 3.10
Classifier: Programming Language :: Python :: 3.13
Classifier: License :: OSI Approved :: MIT License
Classifier: Operating System :: OS Independent
Requires-Python: >=3.10
License-File: LICENSE
Requires-Dist: redis>=5.0.4
Provides-Extra: dev
Requires-Dist: pytest; extra == "dev"
Requires-Dist: fakeredis; extra == "dev"
Requires-Dist: black; extra == "dev"
Requires-Dist: isort; extra == "dev"
Requires-Dist: mypy; extra == "dev"
Requires-Dist: flake8; extra == "dev"
Requires-Dist: build; extra == "dev"
Requires-Dist: twine; extra == "dev"
Provides-Extra: h3
Requires-Dist: h3; extra == "h3"
Dynamic: license-file
